pyaugmecon/__init__.py
pyaugmecon/flag.py
pyaugmecon/helper.py
pyaugmecon/logs.py
pyaugmecon/model.py
pyaugmecon/options.py
pyaugmecon/process_handler.py
pyaugmecon/pyaugmecon.py
pyaugmecon/queue_handler.py
pyaugmecon/solver_process.py
pyaugmecon-1.0.8.dist-info/LICENSE
pyaugmecon-1.0.8.dist-info/METADATA
pyaugmecon-1.0.8.dist-info/WHEEL
pyaugmecon-1.0.8.dist-info/top_level.txt
pyaugmecon-1.0.8.dist-info/RECORD
