Metadata-Version: 2.1
Name: pyaugmecon
Version: 1.0.8
Summary: An AUGMECON based multi-objective optimization solver for Pyomo.
Author-email: Wouter Bles <whbles@gmail.com>
License: MIT License
Project-URL: Homepage, https://github.com/wouterbles/pyaugmecon
Project-URL: Changelog, https://github.com/wouterbles/pyaugmecon/blob/main/CHANGELOG.md
Keywords: python,pyomo,optimization,multi-objective-optimization,augmecon
Classifier: Development Status :: 5 - Production/Stable
Classifier: Intended Audience :: Science/Research
Classifier: Intended Audience :: Education
Classifier: Intended Audience :: Other Audience
Classifier: License :: OSI Approved :: MIT License
Classifier: Operating System :: OS Independent
Classifier: Programming Language :: Python
Classifier: Programming Language :: Python :: 3.8
Classifier: Programming Language :: Python :: 3.9
Classifier: Programming Language :: Python :: 3.10
Classifier: Programming Language :: Python :: 3.11
Classifier: Programming Language :: Python :: 3.12
Classifier: Programming Language :: Python :: 3 :: Only
Classifier: Natural Language :: English
Classifier: Topic :: Scientific/Engineering
Classifier: Topic :: Scientific/Engineering :: Mathematics
Classifier: Topic :: Education
Requires-Python: >=3.8
License-File: LICENSE
Requires-Dist: pyomo ~=6.6
Requires-Dist: numpy ~=1.25
Requires-Dist: pandas ~=2.0
Requires-Dist: cloudpickle ~=3.0
Requires-Dist: pymoo ~=0.6
Requires-Dist: openpyxl ~=3.1
Provides-Extra: dev
Requires-Dist: build ; extra == 'dev'
Requires-Dist: twine ; extra == 'dev'
